Metadata-Version: 2.1
Name: pandoc-docx-pagebreak
Version: 0.0.2
Summary: Pandoc filter for docx output to insert pagebreak at will
Home-page: https://github.com/pandocker/pandoc-docx-pagebreak-py
Author: Kazuki Yamamoto, pandocker
Author-email: k.yamamoto.08136891@gmail.com
License: UNKNOWN
Keywords: pandoc filter docx
Platform: UNKNOWN
Classifier: Development Status :: 3 - Alpha
Classifier: Intended Audience :: Developers
Classifier: Topic :: Software Development :: Build Tools
Classifier: License :: OSI Approved :: MIT License
Classifier: Programming Language :: Python :: 3
Classifier: Programming Language :: Python :: 3.4
Classifier: Programming Language :: Python :: 3.5
Classifier: Programming Language :: Python :: 3.6
